{
"leader_id": "<0.125.0>", "color": "purple", "server_id": "<0.79.0>", "adj_clusters": [{"pid": "<0.126.0>", "color": "green", "leader_id": "<0.118.0>"},{"pid": "<0.124.0>", "color": "red", "leader_id": "<0.103.0>"},{"pid": "<0.119.0>", "color": "red", "leader_id": "<0.91.0>"},{"pid": "<0.118.0>", "color": "green", "leader_id": "<0.118.0>"},{"pid": "<0.117.0>", "color": "red", "leader_id": "<0.103.0>"}], "nodes_in_cluster": ["<0.125.0>"],
"node": {
"x": 7, "y": 4, "parent": "<0.79.0>", "children": [], "time": "undefined", "leader_id": "<0.125.0>", "pid": "<0.125.0>", "neighbors": []
}}